rundoc/__init__.py
rundoc/__main__.py
rundoc/block.py
rundoc/commander.py
rundoc/parsers.py
rundoc-0.4.3.dist-info/AUTHORS
rundoc-0.4.3.dist-info/LICENSE
rundoc-0.4.3.dist-info/METADATA
rundoc-0.4.3.dist-info/WHEEL
rundoc-0.4.3.dist-info/entry_points.txt
rundoc-0.4.3.dist-info/top_level.txt
rundoc-0.4.3.dist-info/RECORD
