Metadata-Version: 2.1
Name: rundoc
Version: 0.4.3
Summary: A command-line utility that runs code blocks from markdown files.
Home-page: https://gitlab.com/nul.one/rundoc
Author: Predrag Mandic
Author-email: predrag@eclecticiq.com
License: BSD
Download-URL: https://gitlab.com/nul.one/rundoc/-/archive/0.4.3/rundoc-0.4.3.tar.gz
Platform: UNKNOWN
Classifier: Development Status :: 4 - Beta
Classifier: Environment :: Console
Classifier: Intended Audience :: Customer Service
Classifier: Intended Audience :: Developers
Classifier: Intended Audience :: Information Technology
Classifier: Intended Audience :: System Administrators
Classifier: License :: OSI Approved :: BSD License
Classifier: Natural Language :: English
Classifier: Operating System :: POSIX :: Linux
Classifier: Programming Language :: Python :: 3 :: Only
Classifier: Topic :: Documentation
Classifier: Topic :: Software Development :: Documentation
Classifier: Topic :: Software Development :: Testing
Classifier: Topic :: Utilities
Requires-Python: >=3.4.6
Requires-Dist: beautifulsoup4 (<5.0,>=4.4.1)
Requires-Dist: click (<8.0,>=6.7)
Requires-Dist: markdown (<3.0,>=2.6.9)
Requires-Dist: markdown-rundoc (<0.4.0,>=0.3.1)
Requires-Dist: prompt-toolkit (<3.0,>=2.0)
Requires-Dist: pygments (<3.0,>=2.2.0)
